timst/__init__.py
timst/run.py
timst/utils.py
timst-0.2.1.dist-info/LICENSE
timst-0.2.1.dist-info/METADATA
timst-0.2.1.dist-info/WHEEL
timst-0.2.1.dist-info/entry_points.txt
timst-0.2.1.dist-info/top_level.txt
timst-0.2.1.dist-info/RECORD
