Metadata-Version: 2.1
Name: timst
Version: 0.2.1
Summary: Image style transfer using Torch
Home-page: https://github.com/Radonirinaunimi/Style-Transfer
Author: Tanjona R. Rabemananjara
Author-email: tanjona.rabemananjara@mi.infn.it
License: UNKNOWN
Platform: UNKNOWN
Classifier: Operating System :: Unix
Classifier: Programming Language :: Python
Classifier: Programming Language :: Python :: 3
Classifier: Topic :: Scientific/Engineering
Classifier: Topic :: Scientific/Engineering :: Physics
Requires-Python: >=3.6
Requires-Dist: numpy
Requires-Dist: torch
Requires-Dist: tqdm
Requires-Dist: torchvision
Provides-Extra: docs
Requires-Dist: recommonmark ; extra == 'docs'
Requires-Dist: sphinx-rtd-theme ; extra == 'docs'
Requires-Dist: sphinxcontrib-bibtex ; extra == 'docs'
Provides-Extra: tests
Requires-Dist: pytest ; extra == 'tests'
Requires-Dist: pytest-cov ; extra == 'tests'
